MANIFEST.in
README.rst
setup.cfg
setup.py
versioneer.py
docser/__init__.py
docser/__main__.py
docser/_version.py
docser.egg-info/PKG-INFO
docser.egg-info/SOURCES.txt
docser.egg-info/dependency_links.txt
docser.egg-info/requires.txt
docser.egg-info/top_level.txt