Metadata-Version: 2.1
Name: docser
Version: 0.0.2
Summary: A simple server for hosting Sphinx documentation
Home-page: https://github.com/chrisbrake/docser
Author: Chris Brake
Author-email: chris.brake@gmail.com
License: UNKNOWN
Keywords: docser,Sphinx,documentation
Platform: UNKNOWN
Classifier: License :: OSI Approved :: BSD License
Classifier: Programming Language :: Python
